README.rst
setup.cfg
setup.py
xdelta3/__init__.py
xdelta3/_xdelta3.c
xdelta3/main.py
xdelta3/version.py
xdelta3/lib/xdelta3-blkcache.h
xdelta3/lib/xdelta3-cfgs.h
xdelta3/lib/xdelta3-decode.h
xdelta3/lib/xdelta3-djw.h
xdelta3/lib/xdelta3-fgk.h
xdelta3/lib/xdelta3-hash.h
xdelta3/lib/xdelta3-internal.h
xdelta3/lib/xdelta3-list.h
xdelta3/lib/xdelta3-lzma.h
xdelta3/lib/xdelta3-main.h
xdelta3/lib/xdelta3-merge.h
xdelta3/lib/xdelta3-second.h
xdelta3/lib/xdelta3.c
xdelta3/lib/xdelta3.h
xdelta3_accemate.egg-info/PKG-INFO
xdelta3_accemate.egg-info/SOURCES.txt
xdelta3_accemate.egg-info/dependency_links.txt
xdelta3_accemate.egg-info/top_level.txt
xdelta3_accemate.egg-info/zip-safe