Metadata-Version: 1.1
Name: xdelta3-accemate
Version: 0.0.6a3
Summary: Fast delta encoding using xdelta3
Home-page: https://github.com/samuelcolvin/xdelta3-python
Author: Samuel Colvin
Author-email: s@muelcolvin.com
License: Apache License, Version 2.0
Platform: UNKNOWN
Classifier: Development Status :: 4 - Beta
Classifier: Programming Language :: Python
Classifier: Programming Language :: Python :: 3
Classifier: Programming Language :: Python :: 3.5
Classifier: Programming Language :: Python :: 3.6
Classifier: License :: OSI Approved :: Apache Software License
Classifier: Operating System :: Unix
Classifier: Operating System :: POSIX :: Linux
Classifier: Topic :: System :: Archiving :: Compression
